README.md
setup.py
ntc/__init__.py
ntc/names.py
ntc/ntc.py
ntc/utils.py
ntcpy.egg-info/PKG-INFO
ntcpy.egg-info/SOURCES.txt
ntcpy.egg-info/dependency_links.txt
ntcpy.egg-info/top_level.txt