Metadata-Version: 2.1
Name: ntcpy
Version: 1.0.0
Summary: A Python port of ntcjs
Home-page: https://github.com/vrumger/ntcpy
Author: Avrumy
Author-email: contact@lungers.com
License: MIT
Platform: UNKNOWN
